PythonPi.py
setup.py
PythonPi.egg-info/PKG-INFO
PythonPi.egg-info/SOURCES.txt
PythonPi.egg-info/dependency_links.txt
PythonPi.egg-info/entry_points.txt
PythonPi.egg-info/top_level.txt