Metadata-Version: 1.1
Name: PythonPi
Version: 1.0.2
Summary: Get the Value of Pi upto as many decimal places as needed
Home-page: https://github.com/geekpradd/PythonPi
Author: Pradipta Bora
Author-email: pradd@outlook.com
License: MIT
Keywords: pi maths
Platform: UNKNOWN
Classifier: Development Status :: 5 - Production/Stable
Classifier: Topic :: Utilities
Classifier: License :: OSI Approved :: MIT License
Classifier: Operating System :: OS Independent
Classifier: Programming Language :: Python
